monk_tf/general_purpose.py
monk_tf/conn.py
monk_tf/__init__.py
monk_tf/dev.py
monk_tf/fixture.py
monk_tf-0.17.8.dist-info/WHEEL
monk_tf-0.17.8.dist-info/DESCRIPTION.rst
monk_tf-0.17.8.dist-info/metadata.json
monk_tf-0.17.8.dist-info/METADATA
monk_tf-0.17.8.dist-info/RECORD
monk_tf-0.17.8.dist-info/top_level.txt
