Metadata-Version: 2.0
Name: monk-tf
Version: 0.17.8
Summary: regression test scripting framework for embedded systems developers
Home-page: https://github.com/DFE/MONK
Author: DResearch Fahrzeugelektronik GmbH
Author-email: project-monk@dresearch-fe.de
License: GNU GENERAL PUBLIC LICENSE
Requires-Dist: pexpect (>=3.3)
Requires-Dist: requests (>=2.2.1)
Requires-Dist: pyte (>=0.4.8)
Requires-Dist: configobj (>=4.7.2)
